vllm/__init__.py
vllm/_custom_ops.py
vllm/block.py
vllm/config.py
vllm/envs.py
vllm/logger.py
vllm/outputs.py
vllm/py.typed
vllm/sampling_params.py
vllm/sequence.py
vllm/test_utils.py
vllm/utils.py
vllm/attention/__init__.py
vllm/attention/layer.py
vllm/attention/selector.py
vllm/attention/backends/__init__.py
vllm/attention/backends/abstract.py
vllm/attention/backends/flash_attn.py
vllm/attention/backends/flashinfer.py
vllm/attention/backends/rocm_flash_attn.py
vllm/attention/backends/torch_sdpa.py
vllm/attention/backends/xformers.py
vllm/attention/ops/__init__.py
vllm/attention/ops/paged_attn.py
vllm/attention/ops/prefix_prefill.py
vllm/attention/ops/triton_flash_attention.py
vllm/core/__init__.py
vllm/core/block_manager_v1.py
vllm/core/block_manager_v2.py
vllm/core/evictor_v1.py
vllm/core/evictor_v2.py
vllm/core/interfaces.py
vllm/core/policy.py
vllm/core/scheduler.py
vllm/core/block/__init__.py
vllm/core/block/block_table.py
vllm/core/block/common.py
vllm/core/block/cpu_gpu_block_allocator.py
vllm/core/block/interfaces.py
vllm/core/block/naive_block.py
vllm/core/block/prefix_caching_block.py
vllm/distributed/__init__.py
vllm/distributed/communication_op.py
vllm/distributed/parallel_state.py
vllm/distributed/utils.py
vllm/distributed/device_communicators/__init__.py
vllm/distributed/device_communicators/custom_all_reduce.py
vllm/distributed/device_communicators/pynccl.py
vllm/distributed/device_communicators/pynccl_utils.py
vllm/engine/__init__.py
vllm/engine/arg_utils.py
vllm/engine/async_llm_engine.py
vllm/engine/llm_engine.py
vllm/engine/metrics.py
vllm/engine/output_processor/__init__.py
vllm/engine/output_processor/interfaces.py
vllm/engine/output_processor/multi_step.py
vllm/engine/output_processor/single_step.py
vllm/engine/output_processor/stop_checker.py
vllm/engine/output_processor/util.py
vllm/entrypoints/__init__.py
vllm/entrypoints/api_server.py
vllm/entrypoints/llm.py
vllm/entrypoints/openai/__init__.py
vllm/entrypoints/openai/api_server.py
vllm_npu-0.4.2.post2.dist-info/LICENSE
vllm_npu-0.4.2.post2.dist-info/METADATA
vllm_npu-0.4.2.post2.dist-info/WHEEL
vllm_npu-0.4.2.post2.dist-info/top_level.txt
vllm_npu-0.4.2.post2.dist-info/RECORD
