Metadata-Version: 2.2
Name: vllm-npu
Version: 0.4.2.post2
Summary: A high-throughput and memory-efficient inference and serving engine for LLMs
Home-page: https://github.com/vllm-project/vllm
Author: vLLM Team
License: Apache 2.0
Project-URL: Homepage, https://github.com/vllm-project/vllm
Project-URL: Documentation, https://vllm.readthedocs.io/en/latest/
Classifier: Programming Language :: Python :: 3.8
Classifier: Programming Language :: Python :: 3.9
Classifier: Programming Language :: Python :: 3.10
Classifier: Programming Language :: Python :: 3.11
Classifier: License :: OSI Approved :: Apache Software License
Classifier: Topic :: Scientific/Engineering :: Artificial Intelligence
Requires-Python: >=3.8
License-File: LICENSE
Requires-Dist: cmake>=3.21
Requires-Dist: ninja
Requires-Dist: psutil
Requires-Dist: sentencepiece
Requires-Dist: numpy==1.26.4
Requires-Dist: requests
Requires-Dist: py-cpuinfo
Requires-Dist: transformers>=4.40.0
Requires-Dist: tokenizers>=0.19.1
Requires-Dist: fastapi
Requires-Dist: openai
Requires-Dist: uvicorn[standard]
Requires-Dist: pydantic>=2.0
Requires-Dist: prometheus_client>=0.18.0
Requires-Dist: prometheus-fastapi-instrumentator>=7.0.0
Requires-Dist: tiktoken==0.6.0
Requires-Dist: lm-format-enforcer==0.10.1
Requires-Dist: typing_extensions
Requires-Dist: filelock>=3.10.4
Requires-Dist: ray==2.9.3
Requires-Dist: pynvml==11.5.0
Requires-Dist: outlines==0.0.34
Requires-Dist: npu-vllm==0.4.2.post3
Provides-Extra: tensorizer
Requires-Dist: tensorizer==2.9.0; extra == "tensorizer"
Dynamic: author
Dynamic: classifier
Dynamic: description
Dynamic: description-content-type
Dynamic: home-page
Dynamic: license
Dynamic: project-url
Dynamic: provides-extra
Dynamic: requires-dist
Dynamic: requires-python
Dynamic: summary
